canvas_science/__init__.py
canvas_science/action.py
canvas_science/cds_client.py
canvas_science/events.py
canvas_science/patient.py
canvas_science/protocol.py
canvas_science/recommendation.py
canvas_science/timeframe.py
canvas_science/value_set/__init__.py
canvas_science/value_set/v2017.py
canvas_science/value_set/v2018.py
canvas_science/value_set/value_set.py
canvas_science-4.0.0.dist-info/DESCRIPTION.rst
canvas_science-4.0.0.dist-info/METADATA
canvas_science-4.0.0.dist-info/RECORD
canvas_science-4.0.0.dist-info/WHEEL
canvas_science-4.0.0.dist-info/metadata.json
canvas_science-4.0.0.dist-info/top_level.txt
