Metadata-Version: 2.0
Name: canvas-science
Version: 4.0.0
Summary: Canvas Medical's Science SDK
Home-page: https://github.com/canvas-medical/science-sdk
Author: Canvas Medical
Author-email: engineering@canvasmedical.com
License: UNKNOWN
Keywords: healthcare science sdk ehr
Platform: UNKNOWN
Classifier: Development Status :: 3 - Alpha
Classifier: Environment :: Console
Classifier: Environment :: Web Environment
Classifier: Intended Audience :: Developers
Classifier: Intended Audience :: Healthcare Industry
Classifier: Operating System :: MacOS :: MacOS X
Classifier: Operating System :: POSIX
Classifier: Programming Language :: Python
Classifier: Programming Language :: Python :: 3
Classifier: Topic :: Software Development :: Libraries
Requires-Dist: arrow (>=0.10)
Requires-Dist: requests (>=2.18)
